README.md
setup.py
allure/__init__.py
allure/allure.py
aqa_core.egg-info/PKG-INFO
aqa_core.egg-info/SOURCES.txt
aqa_core.egg-info/dependency_links.txt
aqa_core.egg-info/not-zip-safe
aqa_core.egg-info/requires.txt
aqa_core.egg-info/top_level.txt
drivers/__init__.py
drivers/base_driver.py
drivers/driver_factory.py
drivers/driver_target_error.py
drivers/event_wrapper.py
drivers/mobile/LOCATORS.py
drivers/mobile/__init__.py
drivers/mobile/driver.py
drivers/mobile/mobile_device.py
drivers/platform/__init__.py
drivers/platform/error.py
drivers/platform/platforms.py
drivers/web/__init__.py
drivers/web/browsers.py
drivers/web/driver.py
helper/__init__.py
helper/echo.py
helper/helper.py
locators/__init__.py
locators/by.py
locators/dynamic_value_error.py
locators/empty_error.py
locators/locator.py
pages/__init__.py
pages/base_page.py
pages/error.py
pages/loader.py
pages/no_such_page_in_storage_error.py
pages/page_storage.py
steps/__init__.py
steps/steps_wrapper.py