Metadata-Version: 2.1
Name: aqa-core
Version: 12.7.2021
Summary: AQA Core
Home-page: https://github.com/remedyproduct/aqa-core
Author: Ivan Veramyou
Author-email: ivan.veramyou22@gmail.com
License: unlicense
Platform: UNKNOWN
Classifier: Programming Language :: Python :: 3
Classifier: Operating System :: OS Independent
Classifier: License :: OSI Approved :: MIT License
Requires-Python: >=3.7
